{
  "type_description_msg": {
    "type_description": {
      "type_name": "my_robot_interfaces/srv/ActivateTurtle_Event",
      "fields": [
        {
          "name": "info",
          "type": {
            "type_id": 1,
            "capacity": 0,
            "string_capacity": 0,
            "nested_type_name": "service_msgs/msg/ServiceEventInfo"
          },
          "default_value": ""
        },
        {
          "name": "request",
          "type": {
            "type_id": 97,
            "capacity": 1,
            "string_capacity": 0,
            "nested_type_name": "my_robot_interfaces/srv/ActivateTurtle_Request"
          },
          "default_value": ""
        },
        {
          "name": "response",
          "type": {
            "type_id": 97,
            "capacity": 1,
            "string_capacity": 0,
            "nested_type_name": "my_robot_interfaces/srv/ActivateTurtle_Response"
          },
          "default_value": ""
        }
      ]
    },
    "referenced_type_descriptions": [
      {
        "type_name": "builtin_interfaces/msg/Time",
        "fields": [
          {
            "name": "sec",
            "type": {
              "type_id": 6,
              "capacity": 0,
              "string_capacity": 0,
              "nested_type_name": ""
            },
            "default_value": ""
          },
          {
            "name": "nanosec",
            "type": {
              "type_id": 7,
              "capacity": 0,
              "string_capacity": 0,
              "nested_type_name": ""
            },
            "default_value": ""
          }
        ]
      },
      {
        "type_name": "my_robot_interfaces/srv/ActivateTurtle_Request",
        "fields": [
          {
            "name": "activate",
            "type": {
              "type_id": 15,
              "capacity": 0,
              "string_capacity": 0,
              "nested_type_name": ""
            },
            "default_value": ""
          }
        ]
      },
      {
        "type_name": "my_robot_interfaces/srv/ActivateTurtle_Response",
        "fields": [
          {
            "name": "message",
            "type": {
              "type_id": 17,
              "capacity": 0,
              "string_capacity": 0,
              "nested_type_name": ""
            },
            "default_value": ""
          }
        ]
      },
      {
        "type_name": "service_msgs/msg/ServiceEventInfo",
        "fields": [
          {
            "name": "event_type",
            "type": {
              "type_id": 3,
              "capacity": 0,
              "string_capacity": 0,
              "nested_type_name": ""
            },
            "default_value": ""
          },
          {
            "name": "stamp",
            "type": {
              "type_id": 1,
              "capacity": 0,
              "string_capacity": 0,
              "nested_type_name": "builtin_interfaces/msg/Time"
            },
            "default_value": ""
          },
          {
            "name": "client_gid",
            "type": {
              "type_id": 51,
              "capacity": 16,
              "string_capacity": 0,
              "nested_type_name": ""
            },
            "default_value": ""
          },
          {
            "name": "sequence_number",
            "type": {
              "type_id": 8,
              "capacity": 0,
              "string_capacity": 0,
              "nested_type_name": ""
            },
            "default_value": ""
          }
        ]
      }
    ]
  },
  "type_hashes": [
    {
      "type_name": "my_robot_interfaces/srv/ActivateTurtle_Event",
      "hash_string": "RIHS01_eadcf6c7161dfe2ae5457626635f9044e5d1e0c6d28966f747c6f21b794c8b27"
    },
    {
      "type_name": "builtin_interfaces/msg/Time",
      "hash_string": "RIHS01_b106235e25a4c5ed35098aa0a61a3ee9c9b18d197f398b0e4206cea9acf9c197"
    },
    {
      "type_name": "my_robot_interfaces/srv/ActivateTurtle_Request",
      "hash_string": "RIHS01_903468a131859d13612d1ce949511fce4863854c64fce947ba4da69d1e6eeeca"
    },
    {
      "type_name": "my_robot_interfaces/srv/ActivateTurtle_Response",
      "hash_string": "RIHS01_1f64469c686472be63e91272ee08fb94970c07ec543c7ecaeba42cb53ef62069"
    },
    {
      "type_name": "service_msgs/msg/ServiceEventInfo",
      "hash_string": "RIHS01_41bcbbe07a75c9b52bc96bfd5c24d7f0fc0a08c0cb7921b3373c5732345a6f45"
    }
  ]
}